[
  {
    "gen": 1,
    "wr": 0.375,
    "promoted": false,
    "elapsed": 32.83
  },
  {
    "gen": 2,
    "wr": 0.5,
    "promoted": false,
    "elapsed": 30.46
  },
  {
    "gen": 3,
    "wr": 0.0,
    "promoted": false,
    "elapsed": 29.82
  },
  {
    "gen": 4,
    "wr": 0.625,
    "promoted": false,
    "elapsed": 29.78
  },
  {
    "gen": 5,
    "wr": 0.625,
    "promoted": false,
    "elapsed": 33.94
  },
  {
    "gen": 6,
    "wr": 0.5,
    "promoted": false,
    "elapsed": 31.65
  },
  {
    "gen": 7,
    "wr": 0.375,
    "promoted": false,
    "elapsed": 30.39
  },
  {
    "gen": 8,
    "wr": 0.5,
    "promoted": false,
    "elapsed": 29.14
  },
  {
    "gen": 9,
    "wr": 0.375,
    "promoted": false,
    "elapsed": 29.56
  },
  {
    "gen": 10,
    "wr": 0.625,
    "promoted": false,
    "elapsed": 30.05
  },
  {
    "gen": 11,
    "wr": 0.125,
    "promoted": false,
    "elapsed": 33.44
  },
  {
    "gen": 12,
    "wr": 0.5,
    "promoted": false,
    "elapsed": 34.44
  },
  {
    "gen": 13,
    "wr": 0.375,
    "promoted": false,
    "elapsed": 31.61
  },
  {
    "gen": 14,
    "wr": 0.625,
    "promoted": false,
    "elapsed": 29.24
  },
  {
    "gen": 15,
    "wr": 0.375,
    "promoted": false,
    "elapsed": 29.13
  },
  {
    "gen": 16,
    "wr": 0.3125,
    "promoted": false,
    "elapsed": 28.98
  },
  {
    "gen": 17,
    "wr": 0.625,
    "promoted": false,
    "elapsed": 30.3
  },
  {
    "gen": 18,
    "wr": 0.75,
    "promoted": true,
    "elapsed": 34.56
  },
  {
    "gen": 19,
    "wr": 0.5,
    "promoted": false,
    "elapsed": 32.36
  },
  {
    "gen": 20,
    "wr": 0.5,
    "promoted": false,
    "elapsed": 34.84
  },
  {
    "gen": 21,
    "wr": 0.375,
    "promoted": false,
    "elapsed": 30.05
  },
  {
    "gen": 22,
    "wr": 0.5,
    "promoted": false,
    "elapsed": 28.77
  },
  {
    "gen": 23,
    "wr": 0.5,
    "promoted": false,
    "elapsed": 29.88
  },
  {
    "gen": 24,
    "wr": 0.625,
    "promoted": false,
    "elapsed": 28.77
  }
]